Metadata-Version: 2.1
Name: bitio
Version: 0.3.0
Summary: Input/output utilities of a bit-basis file
Home-page: https://github.com/hinohi/bitio
Author: Daiju Nakayama
Author-email: 42.daiju@gmail.com
Classifier: Programming Language :: Python :: 3
Classifier: Programming Language :: Python :: 3 :: Only
Classifier: Development Status :: 3 - Alpha
Classifier: License :: OSI Approved :: MIT License
Classifier: Topic :: Utilities
